[
    {
        "name": "Snowflake_Mountain",
        "chest_unopened_img": "images/items/Base_Balloon.png",
        "chest_opened_img": "images/items/Missing_Balloon.png",
        "access_rules": [
            "$CheckBalloons|2"
        ],
                "map_locations": [
                    {
                        "map": "map1",
                        "x": 73,
                        "y": 62,
                        "size": 28,
                        "border_thickness": 2
                    }
                ],
                "sections": [
                    {
                        "name": "Everfrost Peak 1",
                        "item_count": 1,
                        "access_rules": [
                            "$CheckBalloons|2"
                        ]
                    },
                    {
                        "name": "Walrus Cove 1",
                        "item_count": 1,
                        "access_rules": [
                            "$CheckBalloons|3"
                        ]
                    },
                    {
                        "name": "Snowball Valley 1",
                        "item_count": 1,
                        "access_rules": [
                            "$CheckBalloons|6"
                        ]
                    },
                    {
                        "name": "Frosty Village 1",
                        "item_count": 1,
                        "access_rules": [
                            "$CheckBalloons|9"
                        ]
                    },
                    {
                        "name": "Bluey 1",
                        "chest_unopened_img": "images/items/Bluey.png",
                        "chest_opened_img": "images/items/Missing_Bluey.png",
                        "item_count": 1,
                        "access_rules": [
                            "$CheckSnowBalloons|4"
                        ]
                    },
                    {
                        "name": "Everfrost Peak 2",
                        "item_count": 1,
                        "access_rules": [
                            ["$CheckBalloons|10",
                            "bluey1_clear"]
                        ]
                    },
                    {
                        "name": "Walrus Cove 2",
                        "item_count": 1,
                        "access_rules": [
                            ["$CheckBalloons|11",
                            "bluey1_clear"]
                        ]
                    },
                    {
                        "name": "Snowball Valley 2",
                        "item_count": 1,
                        "access_rules": [
                            ["$CheckBalloons|14",
                            "bluey1_clear"]
                        ]
                    },
                    {
                        "name": "Frosty Village 2",
                        "item_count": 1,
                        "access_rules": [
                            ["$CheckBalloons|16",
                            "bluey1_clear"]
                        ]
                    },
                    {
                        "name": "Bluey 2",
                        "chest_unopened_img": "images/items/Bluey2.png",
                        "chest_opened_img": "images/items/Missing_Bluey.png",
                        "item_count": 1,
                        "access_rules": [
                            ["$CheckSnowBalloons|8",
                            "bluey1_clear"]
                        ]
                    },
                    {
                        "name": "Icicle Pyramid",
                        "item_count": 1,
                        "access_rules": [
                            "snow_key"
                        ]
                    },
                    {
                        "name": "Snow Key",
                        "chest_unopened_img": "images/items/Base_Key.png",
                        "chest_opened_img": "images/items/Missing_Key.png",
                        "item_count": 1,
                        "access_rules": [
                            "$CheckBalloons|6"
                        ]
                    },
                    {
                        "name": "Snow Trophy",
                        "chest_unopened_img": "images/items/Trophy.png",
                        "chest_opened_img": "images/items/Missing_Trophy.png",
                        "item_count": 1,
                        "visibility_rules": [
                            "trophies_unskipped"
                        ],
                        "access_rules": [
                            "bluey2_clear"
                        ]
                    }
                ]
    }
]